blanketdb.py
blanketdb-0.4.0.data/scripts/blanketdb.py
blanketdb-0.4.0.dist-info/AUTHORS.rst
blanketdb-0.4.0.dist-info/LICENSE
blanketdb-0.4.0.dist-info/METADATA
blanketdb-0.4.0.dist-info/WHEEL
blanketdb-0.4.0.dist-info/entry_points.txt
blanketdb-0.4.0.dist-info/top_level.txt
blanketdb-0.4.0.dist-info/RECORD
