Metadata-Version: 2.1
Name: blanketdb
Version: 0.4.0
Summary: A simple HTTP accessible database for IoT projects
Home-page: https://github.com/luphord/blanketdb
Author: luphord
Author-email: luphord@protonmail.com
License: MIT license
Keywords: blanketdb
Platform: UNKNOWN
Classifier: Development Status :: 4 - Beta
Classifier: Intended Audience :: Developers
Classifier: License :: OSI Approved :: MIT License
Classifier: Natural Language :: English
Classifier: Programming Language :: Python :: 3
Classifier: Programming Language :: Python :: 3.5
Classifier: Programming Language :: Python :: 3.6
Classifier: Programming Language :: Python :: 3.7
Classifier: Programming Language :: Python :: 3.8
